dash_event_callback/SSE.py
dash_event_callback/__init__.py
dash_event_callback/_event_callback.py
dash_event_callback/_imports_.py
dash_event_callback/async-SSE.js
dash_event_callback/dash_event_callback.js
dash_event_callback/event_callback.py
dash_event_callback/helper.py
dash_event_callback/metadata.json
dash_event_callback/package-info.json
dash_event_callback/proptypes.js
dash_event_callback-1.2.0.dist-info/METADATA
dash_event_callback-1.2.0.dist-info/WHEEL
dash_event_callback-1.2.0.dist-info/entry_points.txt
dash_event_callback-1.2.0.dist-info/RECORD
