Metadata-Version: 2.3
Name: dash-event-callback
Version: 1.2.0
Summary: Streaming callback for Dash
License: MIT
Author: Christian Giessel
Author-email: christian.giessel@gmail.com
Requires-Python: >=3.12
Classifier: License :: OSI Approved :: MIT License
Classifier: Programming Language :: Python :: 3
Classifier: Programming Language :: Python :: 3.12
Classifier: Programming Language :: Python :: 3.13
Requires-Dist: dash (==3.2.0)
